python/rdams_client.py
rda_apps_clients/__init__.py
rda_apps_clients/rdams_client.py
rda_apps_clients-1.0.1.dist-info/LICENSE
rda_apps_clients-1.0.1.dist-info/METADATA
rda_apps_clients-1.0.1.dist-info/WHEEL
rda_apps_clients-1.0.1.dist-info/entry_points.txt
rda_apps_clients-1.0.1.dist-info/top_level.txt
rda_apps_clients-1.0.1.dist-info/RECORD
