Metadata-Version: 2.1
Name: rda-apps-clients
Version: 1.0.1
Summary: Python Client to interact with Research Data Archive's API
Home-page: https://github.com/NCAR/rda-apps-clients
Author: Riley Conroy
Author-email: rpconroy@ucar.edu
License-File: LICENSE
Requires-Dist: requests
